{
    "transforms": [
        {
            "header": {
                "seq": 0,
                "stamp": {
                    "secs": 1687318004,
                    "nsecs": 149579978
                },
                "frame_id": "ra_base"
            },
            "child_frame_id": "ra_tool0_controller",
            "transform": {
                "translation": {
                    "x": -0.6760778843853987,
                    "y": -0.09155406419614615,
                    "z": 0.6376227455360352
                },
                "rotation": {
                    "x": -0.5028173553124633,
                    "y": -0.5053246836368495,
                    "z": 0.4962514056999756,
                    "w": 0.49553628892816337
                }
            }
        }
    ]
}