{
    "transforms": [
        {
            "header": {
                "seq": 0,
                "stamp": {
                    "secs": 1687318027,
                    "nsecs": 397184906
                },
                "frame_id": "ra_base"
            },
            "child_frame_id": "ra_tool0_controller",
            "transform": {
                "translation": {
                    "x": -0.6728261577472198,
                    "y": -0.7293963161267673,
                    "z": 0.6299792744331333
                },
                "rotation": {
                    "x": -0.4907397681075098,
                    "y": -0.5021399029654946,
                    "z": 0.5050323984491286,
                    "w": 0.5019683997666703
                }
            }
        }
    ]
}