{
    "transforms": [
        {
            "header": {
                "seq": 0,
                "stamp": {
                    "secs": 1687318006,
                    "nsecs": 465184906
                },
                "frame_id": "ra_base"
            },
            "child_frame_id": "ra_tool0_controller",
            "transform": {
                "translation": {
                    "x": -0.6760738937418855,
                    "y": -0.09155423354064983,
                    "z": 0.6376393201820967
                },
                "rotation": {
                    "x": -0.5027985696075383,
                    "y": -0.5053312482469018,
                    "z": 0.4962432521147306,
                    "w": 0.4955568208353483
                }
            }
        }
    ]
}