{
    "transforms": [
        {
            "header": {
                "seq": 0,
                "stamp": {
                    "secs": 1687318024,
                    "nsecs": 688822156
                },
                "frame_id": "polhemus_base_0"
            },
            "child_frame_id": "polhemus_station_0",
            "transform": {
                "translation": {
                    "x": 0.04529845342040062,
                    "y": -0.0700749009847641,
                    "z": 0.1415778249502182
                },
                "rotation": {
                    "x": -0.24543218314647675,
                    "y": -0.5864040851593018,
                    "z": -0.14800119400024414,
                    "w": 0.7576203942298889
                }
            }
        },
        {
            "header": {
                "seq": 0,
                "stamp": {
                    "secs": 1687318024,
                    "nsecs": 688822156
                },
                "frame_id": "polhemus_base_0"
            },
            "child_frame_id": "polhemus_station_1",
            "transform": {
                "translation": {
                    "x": 0.13558892905712128,
                    "y": -0.023982910439372063,
                    "z": 0.05084200203418732
                },
                "rotation": {
                    "x": 0.08835259824991226,
                    "y": -0.2857781648635864,
                    "z": 0.10330646485090256,
                    "w": 0.9486055374145508
                }
            }
        },
        {
            "header": {
                "seq": 0,
                "stamp": {
                    "secs": 1687318024,
                    "nsecs": 688822156
                },
                "frame_id": "polhemus_base_0"
            },
            "child_frame_id": "polhemus_station_2",
            "transform": {
                "translation": {
                    "x": 0.14406055212020874,
                    "y": -0.013245555572211742,
                    "z": 0.061489470303058624
                },
                "rotation": {
                    "x": 0.03031589835882187,
                    "y": -0.41288986802101135,
                    "z": -0.1384371817111969,
                    "w": 0.8996877074241638
                }
            }
        },
        {
            "header": {
                "seq": 0,
                "stamp": {
                    "secs": 1687318024,
                    "nsecs": 688822156
                },
                "frame_id": "polhemus_base_0"
            },
            "child_frame_id": "polhemus_station_3",
            "transform": {
                "translation": {
                    "x": 0.12340179085731506,
                    "y": 0.0445169061422348,
                    "z": 0.04037223011255264
                },
                "rotation": {
                    "x": -0.22213931381702423,
                    "y": -0.34514468908309937,
                    "z": -0.09697981178760529,
                    "w": 0.9067104458808899
                }
            }
        },
        {
            "header": {
                "seq": 0,
                "stamp": {
                    "secs": 1687318024,
                    "nsecs": 688822156
                },
                "frame_id": "polhemus_base_0"
            },
            "child_frame_id": "polhemus_station_4",
            "transform": {
                "translation": {
                    "x": 0.138273686170578,
                    "y": 0.061490144580602646,
                    "z": 0.045372169464826584
                },
                "rotation": {
                    "x": 0.4225137233734131,
                    "y": 0.24553196132183075,
                    "z": 0.22031407058238983,
                    "w": -0.8441907167434692
                }
            }
        },
        {
            "header": {
                "seq": 0,
                "stamp": {
                    "secs": 1687318024,
                    "nsecs": 688822156
                },
                "frame_id": "polhemus_base_0"
            },
            "child_frame_id": "polhemus_station_5",
            "transform": {
                "translation": {
                    "x": 0.18831667304039001,
                    "y": 0.05192301794886589,
                    "z": 0.009236805140972137
                },
                "rotation": {
                    "x": 0.2835542857646942,
                    "y": -0.30603787302970886,
                    "z": 0.08675836026668549,
                    "w": -0.9046605825424194
                }
            }
        }
    ]
}