{
    "transforms": [
        {
            "header": {
                "seq": 0,
                "stamp": {
                    "secs": 1687318022,
                    "nsecs": 52477304
                },
                "frame_id": "polhemus_base_0"
            },
            "child_frame_id": "rh_user_forearm",
            "transform": {
                "translation": {
                    "x": -0.18829897046089172,
                    "y": 0.05200957879424095,
                    "z": 0.009225718677043915
                },
                "rotation": {
                    "x": -0.2835575440818476,
                    "y": -0.30628741852977,
                    "z": 0.08621499242288139,
                    "w": 0.9046270565963431
                }
            }
        }
    ]
}