{
    "transforms": [
        {
            "header": {
                "seq": 0,
                "stamp": {
                    "secs": 1687318026,
                    "nsecs": 913788296
                },
                "frame_id": "polhemus_base_0"
            },
            "child_frame_id": "polhemus_station_0",
            "transform": {
                "translation": {
                    "x": 0.04523218795657158,
                    "y": -0.06995401531457901,
                    "z": 0.14166474342346191
                },
                "rotation": {
                    "x": -0.24611517786979675,
                    "y": -0.5865752696990967,
                    "z": -0.147978276014328,
                    "w": 0.7572708129882812
                }
            }
        },
        {
            "header": {
                "seq": 0,
                "stamp": {
                    "secs": 1687318026,
                    "nsecs": 913788296
                },
                "frame_id": "polhemus_base_0"
            },
            "child_frame_id": "polhemus_station_1",
            "transform": {
                "translation": {
                    "x": 0.13559460639953613,
                    "y": -0.023989660665392876,
                    "z": 0.050854239612817764
                },
                "rotation": {
                    "x": 0.08841285854578018,
                    "y": -0.28567594289779663,
                    "z": 0.1032317578792572,
                    "w": 0.9486388564109802
                }
            }
        },
        {
            "header": {
                "seq": 0,
                "stamp": {
                    "secs": 1687318026,
                    "nsecs": 913788296
                },
                "frame_id": "polhemus_base_0"
            },
            "child_frame_id": "polhemus_station_2",
            "transform": {
                "translation": {
                    "x": 0.14406003057956696,
                    "y": -0.013271937146782875,
                    "z": 0.06151039898395538
                },
                "rotation": {
                    "x": 0.0301869697868824,
                    "y": -0.41295868158340454,
                    "z": -0.1385646015405655,
                    "w": 0.8996409177780151
                }
            }
        },
        {
            "header": {
                "seq": 0,
                "stamp": {
                    "secs": 1687318026,
                    "nsecs": 913788296
                },
                "frame_id": "polhemus_base_0"
            },
            "child_frame_id": "polhemus_station_3",
            "transform": {
                "translation": {
                    "x": 0.1234290674328804,
                    "y": 0.04450594633817673,
                    "z": 0.04033883661031723
                },
                "rotation": {
                    "x": -0.22224368155002594,
                    "y": -0.3450216054916382,
                    "z": -0.09720084071159363,
                    "w": 0.9067080616950989
                }
            }
        },
        {
            "header": {
                "seq": 0,
                "stamp": {
                    "secs": 1687318026,
                    "nsecs": 913788296
                },
                "frame_id": "polhemus_base_0"
            },
            "child_frame_id": "polhemus_station_4",
            "transform": {
                "translation": {
                    "x": 0.1383143961429596,
                    "y": 0.061475642025470734,
                    "z": 0.045314010232686996
                },
                "rotation": {
                    "x": 0.423247754573822,
                    "y": 0.24554358422756195,
                    "z": 0.2203301638364792,
                    "w": -0.843815267086029
                }
            }
        },
        {
            "header": {
                "seq": 0,
                "stamp": {
                    "secs": 1687318026,
                    "nsecs": 913788296
                },
                "frame_id": "polhemus_base_0"
            },
            "child_frame_id": "polhemus_station_5",
            "transform": {
                "translation": {
                    "x": 0.18832944333553314,
                    "y": 0.05186346545815468,
                    "z": 0.009291652590036392
                },
                "rotation": {
                    "x": 0.2836310565471649,
                    "y": -0.3056624233722687,
                    "z": 0.08725002408027649,
                    "w": -0.9047161340713501
                }
            }
        }
    ]
}