{
    "transforms": [
        {
            "header": {
                "seq": 0,
                "stamp": {
                    "secs": 1687318001,
                    "nsecs": 221579978
                },
                "frame_id": "ra_base"
            },
            "child_frame_id": "ra_tool0_controller",
            "transform": {
                "translation": {
                    "x": -0.6760685731115661,
                    "y": -0.09154060345122988,
                    "z": 0.6376321832880703
                },
                "rotation": {
                    "x": -0.5028187690032507,
                    "y": -0.5053212226736654,
                    "z": 0.4962358995464747,
                    "w": 0.49555391175425967
                }
            }
        }
    ]
}