{
    "transforms": [
        {
            "header": {
                "seq": 0,
                "stamp": {
                    "secs": 1687318012,
                    "nsecs": 861184906
                },
                "frame_id": "ra_base"
            },
            "child_frame_id": "ra_tool0_controller",
            "transform": {
                "translation": {
                    "x": -0.672824695654623,
                    "y": -0.7293987116217839,
                    "z": 0.6299359561209118
                },
                "rotation": {
                    "x": -0.4907633346641221,
                    "y": -0.5021451482382008,
                    "z": 0.5050004597989899,
                    "w": 0.501972245301466
                }
            }
        }
    ]
}