{
    "transforms": [
        {
            "header": {
                "seq": 0,
                "stamp": {
                    "secs": 1687318026,
                    "nsecs": 751184906
                },
                "frame_id": "ra_base"
            },
            "child_frame_id": "ra_tool0_controller",
            "transform": {
                "translation": {
                    "x": -0.6728524904564146,
                    "y": -0.7293883189291053,
                    "z": 0.6299410089587375
                },
                "rotation": {
                    "x": -0.49073305501891484,
                    "y": -0.5021614550038632,
                    "z": 0.5050100922081192,
                    "w": 0.501975844626166
                }
            }
        }
    ]
}