{
    "transforms": [
        {
            "header": {
                "seq": 0,
                "stamp": {
                    "secs": 1687318008,
                    "nsecs": 611184906
                },
                "frame_id": "ra_base"
            },
            "child_frame_id": "ra_tool0_controller",
            "transform": {
                "translation": {
                    "x": -0.7251763611347772,
                    "y": -0.18297052551244752,
                    "z": 0.6532200981263502
                },
                "rotation": {
                    "x": -0.4993795266336044,
                    "y": -0.5056295507477475,
                    "z": 0.49698409352793965,
                    "w": 0.49796150109224346
                }
            }
        }
    ]
}