{
    "transforms": [
        {
            "header": {
                "seq": 0,
                "stamp": {
                    "secs": 1687318014,
                    "nsecs": 801184906
                },
                "frame_id": "ra_base"
            },
            "child_frame_id": "ra_tool0_controller",
            "transform": {
                "translation": {
                    "x": -0.67285096418282,
                    "y": -0.7293790462205549,
                    "z": 0.6299609456404784
                },
                "rotation": {
                    "x": -0.49074009950072717,
                    "y": -0.502147277751135,
                    "z": 0.5050156488147026,
                    "w": 0.50197754993765
                }
            }
        }
    ]
}