{
    "transforms": [
        {
            "header": {
                "seq": 0,
                "stamp": {
                    "secs": 1687317999,
                    "nsecs": 147164342
                },
                "frame_id": "polhemus_base_0"
            },
            "child_frame_id": "polhemus_station_0",
            "transform": {
                "translation": {
                    "x": 0.04720320180058479,
                    "y": -0.07204727083444595,
                    "z": 0.14038443565368652
                },
                "rotation": {
                    "x": -0.23461546003818512,
                    "y": -0.5791236162185669,
                    "z": -0.14953503012657166,
                    "w": 0.7662967443466187
                }
            }
        },
        {
            "header": {
                "seq": 0,
                "stamp": {
                    "secs": 1687317999,
                    "nsecs": 147164342
                },
                "frame_id": "polhemus_base_0"
            },
            "child_frame_id": "polhemus_station_1",
            "transform": {
                "translation": {
                    "x": 0.13540679216384888,
                    "y": -0.023890795186161995,
                    "z": 0.05096937343478203
                },
                "rotation": {
                    "x": 0.08589838445186615,
                    "y": -0.2873019278049469,
                    "z": 0.1033077985048294,
                    "w": 0.9483703374862671
                }
            }
        },
        {
            "header": {
                "seq": 0,
                "stamp": {
                    "secs": 1687317999,
                    "nsecs": 147164342
                },
                "frame_id": "polhemus_base_0"
            },
            "child_frame_id": "polhemus_station_2",
            "transform": {
                "translation": {
                    "x": 0.1438748985528946,
                    "y": -0.013122722506523132,
                    "z": 0.06158968806266785
                },
                "rotation": {
                    "x": 0.029445212334394455,
                    "y": -0.4145978093147278,
                    "z": -0.1394176036119461,
                    "w": 0.8987794518470764
                }
            }
        },
        {
            "header": {
                "seq": 0,
                "stamp": {
                    "secs": 1687317999,
                    "nsecs": 147164342
                },
                "frame_id": "polhemus_base_0"
            },
            "child_frame_id": "polhemus_station_3",
            "transform": {
                "translation": {
                    "x": 0.12254150211811066,
                    "y": 0.04506784677505493,
                    "z": 0.042068880051374435
                },
                "rotation": {
                    "x": -0.22251105308532715,
                    "y": -0.3533284664154053,
                    "z": -0.09337667375802994,
                    "w": 0.9038407802581787
                }
            }
        },
        {
            "header": {
                "seq": 0,
                "stamp": {
                    "secs": 1687317999,
                    "nsecs": 147164342
                },
                "frame_id": "polhemus_base_0"
            },
            "child_frame_id": "polhemus_station_4",
            "transform": {
                "translation": {
                    "x": 0.1366373747587204,
                    "y": 0.06261181831359863,
                    "z": 0.04705696552991867
                },
                "rotation": {
                    "x": 0.40259984135627747,
                    "y": 0.2510685622692108,
                    "z": 0.21182046830654144,
                    "w": -0.8544061779975891
                }
            }
        },
        {
            "header": {
                "seq": 0,
                "stamp": {
                    "secs": 1687317999,
                    "nsecs": 147164342
                },
                "frame_id": "polhemus_base_0"
            },
            "child_frame_id": "polhemus_station_5",
            "transform": {
                "translation": {
                    "x": 0.18843522667884827,
                    "y": 0.053632259368896484,
                    "z": 0.009671571664512157
                },
                "rotation": {
                    "x": 0.27586284279823303,
                    "y": -0.30518054962158203,
                    "z": 0.07786816358566284,
                    "w": -0.9081305265426636
                }
            }
        }
    ]
}