{
    "transforms": [
        {
            "header": {
                "seq": 0,
                "stamp": {
                    "secs": 1687317999,
                    "nsecs": 955473481
                },
                "frame_id": "polhemus_base_0"
            },
            "child_frame_id": "polhemus_station_0",
            "transform": {
                "translation": {
                    "x": 0.047244615852832794,
                    "y": -0.07201265543699265,
                    "z": 0.14038729667663574
                },
                "rotation": {
                    "x": -0.23476380109786987,
                    "y": -0.5789839625358582,
                    "z": -0.14937928318977356,
                    "w": 0.7663872241973877
                }
            }
        },
        {
            "header": {
                "seq": 0,
                "stamp": {
                    "secs": 1687317999,
                    "nsecs": 955473481
                },
                "frame_id": "polhemus_base_0"
            },
            "child_frame_id": "polhemus_station_1",
            "transform": {
                "translation": {
                    "x": 0.135416179895401,
                    "y": -0.023865671828389168,
                    "z": 0.05095938220620155
                },
                "rotation": {
                    "x": 0.08601587265729904,
                    "y": -0.28728049993515015,
                    "z": 0.10345645993947983,
                    "w": 0.9483500719070435
                }
            }
        },
        {
            "header": {
                "seq": 0,
                "stamp": {
                    "secs": 1687317999,
                    "nsecs": 955473481
                },
                "frame_id": "polhemus_base_0"
            },
            "child_frame_id": "polhemus_station_2",
            "transform": {
                "translation": {
                    "x": 0.14388838410377502,
                    "y": -0.013112291693687439,
                    "z": 0.06156359985470772
                },
                "rotation": {
                    "x": 0.029580984264612198,
                    "y": -0.4143856167793274,
                    "z": -0.1393343061208725,
                    "w": 0.8988857269287109
                }
            }
        },
        {
            "header": {
                "seq": 0,
                "stamp": {
                    "secs": 1687317999,
                    "nsecs": 955473481
                },
                "frame_id": "polhemus_base_0"
            },
            "child_frame_id": "polhemus_station_3",
            "transform": {
                "translation": {
                    "x": 0.12254733592271805,
                    "y": 0.045065637677907944,
                    "z": 0.042027007788419724
                },
                "rotation": {
                    "x": -0.2225407510995865,
                    "y": -0.3531976342201233,
                    "z": -0.09335125982761383,
                    "w": 0.9038873314857483
                }
            }
        },
        {
            "header": {
                "seq": 0,
                "stamp": {
                    "secs": 1687317999,
                    "nsecs": 955473481
                },
                "frame_id": "polhemus_base_0"
            },
            "child_frame_id": "polhemus_station_4",
            "transform": {
                "translation": {
                    "x": 0.1366697996854782,
                    "y": 0.06258916854858398,
                    "z": 0.047000955790281296
                },
                "rotation": {
                    "x": 0.40290021896362305,
                    "y": 0.25084352493286133,
                    "z": 0.21186567842960358,
                    "w": -0.8543194532394409
                }
            }
        },
        {
            "header": {
                "seq": 0,
                "stamp": {
                    "secs": 1687317999,
                    "nsecs": 955473481
                },
                "frame_id": "polhemus_base_0"
            },
            "child_frame_id": "polhemus_station_5",
            "transform": {
                "translation": {
                    "x": 0.18841281533241272,
                    "y": 0.05362921580672264,
                    "z": 0.009625587612390518
                },
                "rotation": {
                    "x": 0.27609574794769287,
                    "y": -0.30555108189582825,
                    "z": 0.07764968276023865,
                    "w": -0.9079537987709045
                }
            }
        }
    ]
}