{
    "transforms": [
        {
            "header": {
                "seq": 0,
                "stamp": {
                    "secs": 1687318009,
                    "nsecs": 627184906
                },
                "frame_id": "ra_base"
            },
            "child_frame_id": "ra_tool0_controller",
            "transform": {
                "translation": {
                    "x": -0.7624957170732667,
                    "y": -0.33419622380397146,
                    "z": 0.6616537256238846
                },
                "rotation": {
                    "x": -0.4954065273145842,
                    "y": -0.505153117716089,
                    "z": 0.4988848764998807,
                    "w": 0.5005063239915337
                }
            }
        }
    ]
}