{
    "transforms": [
        {
            "header": {
                "seq": 0,
                "stamp": {
                    "secs": 1687318008,
                    "nsecs": 149184906
                },
                "frame_id": "ra_base"
            },
            "child_frame_id": "ra_tool0_controller",
            "transform": {
                "translation": {
                    "x": -0.6993065859450609,
                    "y": -0.12905632009250476,
                    "z": 0.645451801028622
                },
                "rotation": {
                    "x": -0.501212208248817,
                    "y": -0.5055371090192474,
                    "z": 0.4965523442773248,
                    "w": 0.4966430540131404
                }
            }
        }
    ]
}