{
    "transforms": [
        {
            "header": {
                "seq": 0,
                "stamp": {
                    "secs": 1687318023,
                    "nsecs": 227469978
                },
                "frame_id": "polhemus_base_0"
            },
            "child_frame_id": "rh_user_forearm",
            "transform": {
                "translation": {
                    "x": -0.18831217288970947,
                    "y": 0.05194083973765373,
                    "z": 0.009204579517245293
                },
                "rotation": {
                    "x": -0.28322849156589364,
                    "y": -0.3063143543544352,
                    "z": 0.08656430390830565,
                    "w": 0.9046876583498884
                }
            }
        }
    ]
}