{
    "transforms": [
        {
            "header": {
                "seq": 0,
                "stamp": {
                    "secs": 1687318010,
                    "nsecs": 238799425
                },
                "frame_id": "polhemus_base_0"
            },
            "child_frame_id": "polhemus_station_0",
            "transform": {
                "translation": {
                    "x": 0.04662272706627846,
                    "y": -0.0712728276848793,
                    "z": 0.14085917174816132
                },
                "rotation": {
                    "x": -0.23965699970722198,
                    "y": -0.5811147093772888,
                    "z": -0.1491486132144928,
                    "w": 0.7632986903190613
                }
            }
        },
        {
            "header": {
                "seq": 0,
                "stamp": {
                    "secs": 1687318010,
                    "nsecs": 238799425
                },
                "frame_id": "polhemus_base_0"
            },
            "child_frame_id": "polhemus_station_1",
            "transform": {
                "translation": {
                    "x": 0.13559627532958984,
                    "y": -0.024164877831935883,
                    "z": 0.050747670233249664
                },
                "rotation": {
                    "x": 0.08786538243293762,
                    "y": -0.2858927249908447,
                    "z": 0.1022254079580307,
                    "w": 0.9487333297729492
                }
            }
        },
        {
            "header": {
                "seq": 0,
                "stamp": {
                    "secs": 1687318010,
                    "nsecs": 238799425
                },
                "frame_id": "polhemus_base_0"
            },
            "child_frame_id": "polhemus_station_2",
            "transform": {
                "translation": {
                    "x": 0.14410603046417236,
                    "y": -0.013481182977557182,
                    "z": 0.061391595751047134
                },
                "rotation": {
                    "x": 0.031187891960144043,
                    "y": -0.412819504737854,
                    "z": -0.14069965481758118,
                    "w": 0.8993392586708069
                }
            }
        },
        {
            "header": {
                "seq": 0,
                "stamp": {
                    "secs": 1687318010,
                    "nsecs": 238799425
                },
                "frame_id": "polhemus_base_0"
            },
            "child_frame_id": "polhemus_station_3",
            "transform": {
                "translation": {
                    "x": 0.1230139508843422,
                    "y": 0.0444926992058754,
                    "z": 0.04093720763921738
                },
                "rotation": {
                    "x": -0.2208811640739441,
                    "y": -0.3483562767505646,
                    "z": -0.0951647162437439,
                    "w": 0.9059817790985107
                }
            }
        },
        {
            "header": {
                "seq": 0,
                "stamp": {
                    "secs": 1687318010,
                    "nsecs": 238799425
                },
                "frame_id": "polhemus_base_0"
            },
            "child_frame_id": "polhemus_station_4",
            "transform": {
                "translation": {
                    "x": 0.13772772252559662,
                    "y": 0.061631593853235245,
                    "z": 0.04603711888194084
                },
                "rotation": {
                    "x": 0.4120991826057434,
                    "y": 0.24530111253261566,
                    "z": 0.21856771409511566,
                    "w": -0.8498410582542419
                }
            }
        },
        {
            "header": {
                "seq": 0,
                "stamp": {
                    "secs": 1687318010,
                    "nsecs": 238799425
                },
                "frame_id": "polhemus_base_0"
            },
            "child_frame_id": "polhemus_station_5",
            "transform": {
                "translation": {
                    "x": 0.18835778534412384,
                    "y": 0.052603933960199356,
                    "z": 0.009474311023950577
                },
                "rotation": {
                    "x": 0.27903249859809875,
                    "y": -0.3062122166156769,
                    "z": 0.08262820541858673,
                    "w": -0.906392514705658
                }
            }
        }
    ]
}