{
    "transforms": [
        {
            "header": {
                "seq": 0,
                "stamp": {
                    "secs": 1687318001,
                    "nsecs": 638823849
                },
                "frame_id": "polhemus_base_0"
            },
            "child_frame_id": "polhemus_station_0",
            "transform": {
                "translation": {
                    "x": 0.04719528183341026,
                    "y": -0.07197077572345734,
                    "z": 0.14042434096336365
                },
                "rotation": {
                    "x": -0.23519444465637207,
                    "y": -0.579065203666687,
                    "z": -0.1495378315448761,
                    "w": 0.7661628127098083
                }
            }
        },
        {
            "header": {
                "seq": 0,
                "stamp": {
                    "secs": 1687318001,
                    "nsecs": 638823849
                },
                "frame_id": "polhemus_base_0"
            },
            "child_frame_id": "polhemus_station_1",
            "transform": {
                "translation": {
                    "x": 0.13542841374874115,
                    "y": -0.023904576897621155,
                    "z": 0.05096150562167168
                },
                "rotation": {
                    "x": 0.0861750915646553,
                    "y": -0.2871708571910858,
                    "z": 0.10330863296985626,
                    "w": 0.9483848214149475
                }
            }
        },
        {
            "header": {
                "seq": 0,
                "stamp": {
                    "secs": 1687318001,
                    "nsecs": 638823849
                },
                "frame_id": "polhemus_base_0"
            },
            "child_frame_id": "polhemus_station_2",
            "transform": {
                "translation": {
                    "x": 0.14389826357364655,
                    "y": -0.013127815909683704,
                    "z": 0.06157560274004936
                },
                "rotation": {
                    "x": 0.029888425022363663,
                    "y": -0.41442373394966125,
                    "z": -0.13922080397605896,
                    "w": 0.8988755345344543
                }
            }
        },
        {
            "header": {
                "seq": 0,
                "stamp": {
                    "secs": 1687318001,
                    "nsecs": 638823849
                },
                "frame_id": "polhemus_base_0"
            },
            "child_frame_id": "polhemus_station_3",
            "transform": {
                "translation": {
                    "x": 0.12258974462747574,
                    "y": 0.04497545212507248,
                    "z": 0.04197446629405022
                },
                "rotation": {
                    "x": -0.2227380871772766,
                    "y": -0.3528127670288086,
                    "z": -0.0942106768488884,
                    "w": 0.9038998484611511
                }
            }
        },
        {
            "header": {
                "seq": 0,
                "stamp": {
                    "secs": 1687318001,
                    "nsecs": 638823849
                },
                "frame_id": "polhemus_base_0"
            },
            "child_frame_id": "polhemus_station_4",
            "transform": {
                "translation": {
                    "x": 0.1367405354976654,
                    "y": 0.062496501952409744,
                    "z": 0.04695650190114975
                },
                "rotation": {
                    "x": 0.40357115864753723,
                    "y": 0.2508190870285034,
                    "z": 0.21250537037849426,
                    "w": -0.8538509607315063
                }
            }
        },
        {
            "header": {
                "seq": 0,
                "stamp": {
                    "secs": 1687318001,
                    "nsecs": 638823849
                },
                "frame_id": "polhemus_base_0"
            },
            "child_frame_id": "polhemus_station_5",
            "transform": {
                "translation": {
                    "x": 0.18844188749790192,
                    "y": 0.05344244837760925,
                    "z": 0.00979384034872055
                },
                "rotation": {
                    "x": 0.2754100561141968,
                    "y": -0.30500727891921997,
                    "z": 0.0787508636713028,
                    "w": -0.9082500338554382
                }
            }
        }
    ]
}